global_exchange_rates/__init__.py
global_exchange_rates/client.py
global_exchange_rates/exceptions.py
global_exchange_rates/models.py
global_exchange_rates-1.0.1.dist-info/licenses/LICENSE
global_exchange_rates-1.0.1.dist-info/METADATA
global_exchange_rates-1.0.1.dist-info/WHEEL
global_exchange_rates-1.0.1.dist-info/top_level.txt
global_exchange_rates-1.0.1.dist-info/RECORD
