Metadata-Version: 2.4
Name: global-exchange-rates
Version: 1.0.1
Summary: A Python client library for interacting with the Global Exchange Rates API
Author-email: Global Exchange Rates <info@globalexchangerates.org>
License-Expression: MIT
Project-URL: Homepage, https://www.globalexchangerates.org/
Project-URL: Documentation, https://doc.globalexchangerates.org/
Keywords: exchange rates,currency,finance,currency rates,currency exchange rates,exchange rates api
Classifier: Development Status :: 5 - Production/Stable
Classifier: Intended Audience :: Developers
Classifier: Programming Language :: Python :: 3
Classifier: Programming Language :: Python :: 3.8
Classifier: Programming Language :: Python :: 3.9
Classifier: Programming Language :: Python :: 3.10
Classifier: Programming Language :: Python :: 3.11
Classifier: Programming Language :: Python :: 3.12
Classifier: Topic :: Software Development :: Libraries :: Python Modules
Classifier: Topic :: Office/Business :: Financial
Requires-Python: >=3.8
License-File: LICENSE
Requires-Dist: httpx>=0.24.0
Requires-Dist: anyio>=3.6.0
Requires-Dist: pydantic>=2.0
Dynamic: license-file
